tests/__init__.py
tests/test_datatype.py
tests/test_datetime.py
tests/test_normalize.py
tests/test_temperature.py
zzam/__init__.py
zzam/datatype.py
zzam/datetime.py
zzam/normalize.py
zzam/temperature.py
zzam/utils/__init__.py
zzam/utils/constants.py
zzam/utils/normalize_helpers.py
zzam-0.0.4.dist-info/METADATA
zzam-0.0.4.dist-info/WHEEL
zzam-0.0.4.dist-info/top_level.txt
zzam-0.0.4.dist-info/RECORD
